{
    "Event": "Seamaster 2019 ITTF Challenge, Thailand Open Men's Singles",
    "PARK Gyeongtae 1:4 CHO Jaejun": "4lfjuXM4a4g",
    "DIAW Ibrahima 1:4 SEO Hyundeok": "ET5JJ-wwUy0",
    "WANG Tai-Wei 4:3 ORT Kilian": "htdfzGR7-vQ",
    "TANAKA Yuta 4:3 OIKAWA Mizuki": "qSLiNf1mWmw",
    "FILUS Ruwen 4:3 SALIFOU Abdel-Kader": "elUh3Fk9ASo",
    "YEH Chih-Wei 4:1 OH Minseo": "rx_2jDupzN8",
    "HUANG Yan-Cheng 1:4 LANDRIEU Andrea": "Sy2c-bpR_1w",
    "BAEK Hogyun 1:4 MATSUDAIRA Kenta": "-43xcqB7nxM",
    "CHO Jaejun 0:4 SEO Hyundeok": "Gw87dG3bFYU",
    "WANG Tai-Wei 2:4 TANAKA Yuta": "htdfzGR7-vQ",
    "FILUS Ruwen 4:0 YEH Chih-Wei": "RvoInPrGxps",
    "LANDRIEU Andrea 4:0 MATSUDAIRA Kenta": "-43xcqB7nxM",
    "SEO Hyundeok 4:3 TANAKA Yuta": "qSLiNf1mWmw",
    "FILUS Ruwen 4:3 LANDRIEU Andrea": "LuvgHcEhY5g",
    "SEO Hyundeok 2:4 FILUS Ruwen": "PDrAnS-Zb0s"
}